spiffyplots/__init__.py
spiffyplots/colors.py
spiffyplots/multipanel.py
tests/__init__.py
tests/test_colors.py
tests/test_multipanel.py
spiffyplots-0.5.1.dist-info/LICENSE
spiffyplots-0.5.1.dist-info/METADATA
spiffyplots-0.5.1.dist-info/WHEEL
spiffyplots-0.5.1.dist-info/top_level.txt
spiffyplots-0.5.1.dist-info/RECORD
