Metadata-Version: 2.1
Name: spiffyplots
Version: 0.5.1
Summary: A collection of matplotlib style sheets and plotting tools for publication-ready figures
Home-page: https://github.com/JRBCH/spiffyplots
Author: Julian Rossbroich
Author-email: julian.rossbroich@fmi.ch
License: GPL-3
Platform: UNKNOWN
Requires-Dist: matplotlib
Requires-Dist: wheel
Requires-Dist: numpy
Provides-Extra: test
Requires-Dist: coverage ; extra == 'test'
Requires-Dist: pytest ; extra == 'test'
Requires-Dist: pytest-cov ; extra == 'test'
